quantecon_wasm/__init__.py
quantecon_wasm/_arma.py
quantecon_wasm/_ce_util.py
quantecon_wasm/_compute_fp.py
quantecon_wasm/_discrete_rv.py
quantecon_wasm/_dle.py
quantecon_wasm/_ecdf.py
quantecon_wasm/_estspec.py
quantecon_wasm/_filter.py
quantecon_wasm/_graph_tools.py
quantecon_wasm/_gridtools.py
quantecon_wasm/_inequality.py
quantecon_wasm/_ivp.py
quantecon_wasm/_kalman.py
quantecon_wasm/_lae.py
quantecon_wasm/_lqcontrol.py
quantecon_wasm/_lqnash.py
quantecon_wasm/_lss.py
quantecon_wasm/_matrix_eqn.py
quantecon_wasm/_quadsums.py
quantecon_wasm/_rank_nullspace.py
quantecon_wasm/_robustlq.py
quantecon_wasm/arma.py
quantecon_wasm/ce_util.py
quantecon_wasm/compute_fp.py
quantecon_wasm/discrete_rv.py
quantecon_wasm/distributions.py
quantecon_wasm/dle.py
quantecon_wasm/ecdf.py
quantecon_wasm/estspec.py
quantecon_wasm/filter.py
quantecon_wasm/graph_tools.py
quantecon_wasm/gridtools.py
quantecon_wasm/inequality.py
quantecon_wasm/ivp.py
quantecon_wasm/kalman.py
quantecon_wasm/lae.py
quantecon_wasm/lqcontrol.py
quantecon_wasm/lqnash.py
quantecon_wasm/lss.py
quantecon_wasm/matrix_eqn.py
quantecon_wasm/quad.py
quantecon_wasm/quadsums.py
quantecon_wasm/rank_nullspace.py
quantecon_wasm/robustlq.py
quantecon_wasm/game_theory/__init__.py
quantecon_wasm/game_theory/brd.py
quantecon_wasm/game_theory/fictplay.py
quantecon_wasm/game_theory/game_converters.py
quantecon_wasm/game_theory/howson_lcp.py
quantecon_wasm/game_theory/lemke_howson.py
quantecon_wasm/game_theory/localint.py
quantecon_wasm/game_theory/logitdyn.py
quantecon_wasm/game_theory/mclennan_tourky.py
quantecon_wasm/game_theory/normal_form_game.py
quantecon_wasm/game_theory/polymatrix_game.py
quantecon_wasm/game_theory/pure_nash.py
quantecon_wasm/game_theory/random.py
quantecon_wasm/game_theory/repeated_game.py
quantecon_wasm/game_theory/support_enumeration.py
quantecon_wasm/game_theory/utilities.py
quantecon_wasm/game_theory/vertex_enumeration.py
quantecon_wasm/game_theory/game_generators/__init__.py
quantecon_wasm-0.7.2.post1.dist-info/LICENSE
quantecon_wasm-0.7.2.post1.dist-info/WHEEL
quantecon_wasm-0.7.2.post1.dist-info/METADATA
quantecon_wasm-0.7.2.post1.dist-info/RECORD
